{"mc":{
	"horse_17_h_1r":{
		"frameRate":12,
		"frames":[
			{"res":"10009","x":-50,"y":-116},
			{"res":"10010","x":-49,"y":-119},
			{"res":"10011","x":-45,"y":-120},
			{"res":"10012","x":-39,"y":-119},
			{"res":"10013","x":-34,"y":-117},
			{"res":"10014","x":-35,"y":-115},
			{"res":"10015","x":-40,"y":-116},
			{"res":"10016","x":-44,"y":-115}
		]
}},
"res":{
	"10009":{"x":276,"y":2,"w":98,"h":84},
	"10010":{"x":94,"y":2,"w":96,"h":90},
	"10011":{"x":2,"y":2,"w":90,"h":92},
	"10012":{"x":192,"y":2,"w":82,"h":90},
	"10013":{"x":376,"y":2,"w":74,"h":84},
	"10014":{"x":630,"y":2,"w":76,"h":80},
	"10015":{"x":544,"y":2,"w":84,"h":80},
	"10016":{"x":452,"y":2,"w":90,"h":80}
}}